ratealert/__init__.py
ratealert/era.py
ratealert/transferwiseclient.py
ratealert/auth/__init__.py
ratealert/auth/linuxauth.py
ratealert/auth/windowsauth.py
ratealert/notification/__init__.py
ratealert/notification/linuxnotification.py
ratealert/notification/windowsnotification.py
exchange_rate_alert-0.8.dist-info/LICENSE
exchange_rate_alert-0.8.dist-info/METADATA
exchange_rate_alert-0.8.dist-info/WHEEL
exchange_rate_alert-0.8.dist-info/entry_points.txt
exchange_rate_alert-0.8.dist-info/top_level.txt
exchange_rate_alert-0.8.dist-info/RECORD
