Metadata-Version: 2.1
Name: exchange-rate-alert
Version: 0.8
Summary: Create desktop alerts for Transferwise exchange rates
Home-page: https://github.com/paradigmwit/exchange-rate-alert
Author: Fahd Mohammed Khan
Author-email: fahd_khan_01@hotmail.com
License: MIT
Platform: UNKNOWN
Classifier: Programming Language :: Python :: 3
Classifier: License :: OSI Approved :: MIT License
Classifier: Operating System :: OS Independent
Requires-Python: >=3.6
Requires-Dist: requests
Requires-Dist: setuptools
Requires-Dist: click
Requires-Dist: pypiwin32 ; sys_platform == "win32"
Requires-Dist: win10toast ; sys_platform == "win32"
